[{"year":1993,"count":1,"died":1,"hosp":0},{"year":1996,"count":1,"died":0,"hosp":1},{"year":2007,"count":1,"died":0,"hosp":0},{"year":2008,"count":13,"died":0,"hosp":13},{"year":2009,"count":2,"died":0,"hosp":0},{"year":2011,"count":1,"died":0,"hosp":1},{"year":2017,"count":1,"died":0,"hosp":1},{"year":2018,"count":2,"died":0,"hosp":1},{"year":2019,"count":1,"died":0,"hosp":0},{"year":2020,"count":1,"died":0,"hosp":0},{"year":2021,"count":31,"died":3,"hosp":15},{"year":2022,"count":22,"died":2,"hosp":19},{"year":2023,"count":10,"died":0,"hosp":8},{"year":2024,"count":4,"died":0,"hosp":4},{"year":2025,"count":4,"died":1,"hosp":0}]