[{"year":1996,"count":1,"died":0,"hosp":0},{"year":1998,"count":5,"died":2,"hosp":2},{"year":1999,"count":9,"died":0,"hosp":3},{"year":2000,"count":625,"died":3,"hosp":58},{"year":2001,"count":590,"died":19,"hosp":79},{"year":2002,"count":481,"died":13,"hosp":48},{"year":2003,"count":825,"died":9,"hosp":103},{"year":2004,"count":785,"died":8,"hosp":76},{"year":2005,"count":940,"died":7,"hosp":112},{"year":2006,"count":846,"died":15,"hosp":151},{"year":2007,"count":1303,"died":6,"hosp":103},{"year":2008,"count":1668,"died":10,"hosp":244},{"year":2009,"count":2167,"died":32,"hosp":316},{"year":2010,"count":2161,"died":9,"hosp":231},{"year":2011,"count":1598,"died":7,"hosp":154},{"year":2012,"count":1720,"died":3,"hosp":150},{"year":2013,"count":1596,"died":23,"hosp":121},{"year":2014,"count":1500,"died":3,"hosp":107},{"year":2015,"count":2104,"died":5,"hosp":178},{"year":2016,"count":2290,"died":18,"hosp":169},{"year":2017,"count":2286,"died":9,"hosp":135},{"year":2018,"count":4462,"died":16,"hosp":163},{"year":2019,"count":4826,"died":8,"hosp":161},{"year":2020,"count":5430,"died":6,"hosp":114},{"year":2021,"count":120882,"died":938,"hosp":6094},{"year":2022,"count":24974,"died":404,"hosp":3172},{"year":2023,"count":7886,"died":105,"hosp":934},{"year":2024,"count":3886,"died":49,"hosp":402},{"year":2025,"count":2641,"died":31,"hosp":230},{"year":2026,"count":53,"died":1,"hosp":11}]