[{"year":1999,"count":1,"died":0,"hosp":0},{"year":2000,"count":660,"died":0,"hosp":23},{"year":2001,"count":717,"died":0,"hosp":25},{"year":2002,"count":1193,"died":0,"hosp":38},{"year":2003,"count":2786,"died":1,"hosp":43},{"year":2004,"count":2801,"died":1,"hosp":34},{"year":2005,"count":2490,"died":0,"hosp":52},{"year":2006,"count":1741,"died":0,"hosp":26},{"year":2007,"count":327,"died":4,"hosp":7},{"year":2008,"count":556,"died":0,"hosp":21},{"year":2009,"count":664,"died":0,"hosp":28},{"year":2010,"count":468,"died":1,"hosp":38},{"year":2011,"count":412,"died":0,"hosp":15},{"year":2012,"count":676,"died":0,"hosp":14},{"year":2013,"count":559,"died":4,"hosp":27},{"year":2014,"count":488,"died":0,"hosp":19},{"year":2015,"count":410,"died":0,"hosp":16},{"year":2016,"count":434,"died":2,"hosp":24},{"year":2017,"count":453,"died":0,"hosp":15},{"year":2018,"count":602,"died":0,"hosp":24},{"year":2019,"count":577,"died":0,"hosp":24},{"year":2020,"count":951,"died":4,"hosp":21},{"year":2021,"count":13265,"died":21,"hosp":353},{"year":2022,"count":1806,"died":2,"hosp":69},{"year":2023,"count":777,"died":3,"hosp":25},{"year":2024,"count":496,"died":0,"hosp":13},{"year":2025,"count":370,"died":0,"hosp":5},{"year":2026,"count":8,"died":0,"hosp":0}]