{"name":"DTAP + IPV (KINRIX)","type":"DTAPIPV","reports":13957,"died":13,"hosp":314,"er":2851,"disabled":76,"yearly":[{"year":2008,"count":46},{"year":2009,"count":658},{"year":2010,"count":870},{"year":2011,"count":640},{"year":2012,"count":638},{"year":2013,"count":732},{"year":2014,"count":690},{"year":2015,"count":711},{"year":2016,"count":756},{"year":2017,"count":842},{"year":2018,"count":921},{"year":2019,"count":878},{"year":2020,"count":655},{"year":2021,"count":764},{"year":2022,"count":1036},{"year":2023,"count":1147},{"year":2024,"count":1074},{"year":2025,"count":896},{"year":2026,"count":3}],"manufacturers":[{"name":"GLAXOSMITHKLINE BIOLOGICALS","count":11538},{"name":"SANOFI PASTEUR","count":2247},{"name":"UNKNOWN MANUFACTURER","count":172}],"ageGroups":{"0-2":2119,"3-17":10858,"18-49":48,"50-64":31,"65+":25,"Unknown":876},"symptoms":[{"name":"Injection site erythema","count":4187},{"name":"Injection site swelling","count":3230},{"name":"Injection site warmth","count":2010},{"name":"Product administered to patient of inappropriate age","count":1852},{"name":"No adverse event","count":1530},{"name":"Injection site pain","count":1350},{"name":"Pyrexia","count":1340},{"name":"Erythema","count":1311},{"name":"Wrong product administered","count":869},{"name":"Urticaria","count":796},{"name":"Injection site induration","count":781},{"name":"Rash","count":656},{"name":"Skin warm","count":599},{"name":"Injection site pruritus","count":584},{"name":"Vomiting","count":556},{"name":"Swelling","count":546},{"name":"Pruritus","count":493},{"name":"Injection site reaction","count":455},{"name":"Injection site rash","count":452},{"name":"Extra dose administered","count":405}]}