{"name":"DTAP+IPV+HIB+HEPB (VAXELIS)","type":"DTPPVHBHPB","reports":2414,"died":30,"hosp":99,"er":217,"disabled":10,"yearly":[{"year":2021,"count":22},{"year":2022,"count":436},{"year":2023,"count":829},{"year":2024,"count":547},{"year":2025,"count":574},{"year":2026,"count":6}],"manufacturers":[{"name":"MSP VACCINE COMPANY","count":2414}],"ageGroups":{"0-2":1175,"3-17":161,"18-49":6,"50-64":4,"65+":6,"Unknown":1062},"symptoms":[{"name":"No adverse event","count":664},{"name":"Pyrexia","count":437},{"name":"Product storage error","count":428},{"name":"Extra dose administered","count":357},{"name":"Product administered to patient of inappropriate age","count":302},{"name":"Wrong product administered","count":283},{"name":"Injection site swelling","count":160},{"name":"Injection site erythema","count":155},{"name":"Crying","count":155},{"name":"Rash","count":151},{"name":"Diarrhoea","count":130},{"name":"Irritability","count":126},{"name":"Erythema","count":115},{"name":"Vomiting","count":114},{"name":"Urticaria","count":97},{"name":"Expired product administered","count":97},{"name":"Inappropriate schedule of product administration","count":91},{"name":"Infant irritability","count":84},{"name":"Seizure","count":68},{"name":"Pallor","count":68}]}