{"name":"HPV (GARDASIL)","type":"HPV4","reports":44434,"died":446,"hosp":2693,"er":15654,"disabled":1758,"yearly":[{"year":2006,"count":506},{"year":2007,"count":6694},{"year":2008,"count":6990},{"year":2009,"count":4106},{"year":2010,"count":3154},{"year":2011,"count":2620},{"year":2012,"count":3639},{"year":2013,"count":3726},{"year":2014,"count":4184},{"year":2015,"count":4025},{"year":2016,"count":2404},{"year":2017,"count":786},{"year":2018,"count":299},{"year":2019,"count":291},{"year":2020,"count":216},{"year":2021,"count":146},{"year":2022,"count":135},{"year":2023,"count":226},{"year":2024,"count":161},{"year":2025,"count":125},{"year":2026,"count":1}],"manufacturers":[{"name":"MERCK & CO. INC.","count":44434}],"ageGroups":{"0-2":204,"3-17":22021,"18-49":11296,"50-64":60,"65+":26,"Unknown":10827},"symptoms":[{"name":"No adverse event","count":6896},{"name":"Syncope","count":6607},{"name":"Dizziness","count":6600},{"name":"Headache","count":5447},{"name":"Nausea","count":4328},{"name":"Pyrexia","count":3246},{"name":"Fatigue","count":3179},{"name":"Loss of consciousness","count":3104},{"name":"Pain","count":2740},{"name":"Incorrect product storage","count":2638},{"name":"Pain in extremity","count":2621},{"name":"Vomiting","count":2614},{"name":"Inappropriate schedule of drug administration","count":2556},{"name":"Injection site pain","count":2541},{"name":"Convulsion","count":2473},{"name":"Injection site erythema","count":2209},{"name":"Pallor","count":2160},{"name":"Rash","count":2065},{"name":"Urticaria","count":2065},{"name":"Hypoaesthesia","count":1963}]}