{"name":"RUBELLA (MERUVAX II)","type":"RUB","reports":1021,"died":3,"hosp":66,"er":420,"disabled":68,"yearly":[{"year":1990,"count":71},{"year":1991,"count":98},{"year":1992,"count":72},{"year":1993,"count":71},{"year":1994,"count":48},{"year":1995,"count":67},{"year":1996,"count":73},{"year":1997,"count":50},{"year":1998,"count":63},{"year":1999,"count":26},{"year":2000,"count":65},{"year":2001,"count":43},{"year":2002,"count":37},{"year":2003,"count":33},{"year":2004,"count":23},{"year":2005,"count":23},{"year":2006,"count":20},{"year":2007,"count":26},{"year":2008,"count":16},{"year":2009,"count":30},{"year":2010,"count":25},{"year":2011,"count":12},{"year":2012,"count":2},{"year":2013,"count":1},{"year":2014,"count":5},{"year":2015,"count":5},{"year":2016,"count":8},{"year":2017,"count":6},{"year":2018,"count":1},{"year":2020,"count":1}],"manufacturers":[{"name":"MERCK & CO. INC.","count":937},{"name":"UNKNOWN MANUFACTURER","count":77},{"name":"SANOFI PASTEUR","count":4},{"name":"BURROUGHS WELLCOME","count":3}],"ageGroups":{"0-2":55,"3-17":29,"18-49":642,"50-64":129,"65+":10,"Unknown":156},"symptoms":[{"name":"Arthralgia","count":386},{"name":"Rash","count":354},{"name":"Pyrexia","count":252},{"name":"Lymphadenopathy","count":163},{"name":"Pain","count":149},{"name":"Pruritus","count":109},{"name":"Arthritis","count":105},{"name":"Headache","count":103},{"name":"Rash maculo-papular","count":100},{"name":"Paraesthesia","count":99},{"name":"Drug ineffective","count":98},{"name":"Myalgia","count":90},{"name":"Asthenia","count":87},{"name":"Oedema peripheral","count":85},{"name":"Osteoarthritis","count":81},{"name":"Pharyngitis","count":76},{"name":"Malaise","count":66},{"name":"Laboratory test abnormal","count":58},{"name":"Hypokinesia","count":53},{"name":"Urticaria","count":49}]}