[{"state":"UNK","reports":1353,"died":10,"hosp":50},{"state":"CA","reports":852,"died":2,"hosp":24},{"state":"TX","reports":720,"died":0,"hosp":20},{"state":"MI","reports":615,"died":0,"hosp":11},{"state":"PA","reports":518,"died":0,"hosp":12},{"state":"NY","reports":512,"died":0,"hosp":17},{"state":"FL","reports":474,"died":1,"hosp":21},{"state":"IN","reports":370,"died":0,"hosp":14},{"state":"GA","reports":362,"died":0,"hosp":11},{"state":"NJ","reports":352,"died":0,"hosp":6},{"state":"OH","reports":324,"died":0,"hosp":7},{"state":"MA","reports":312,"died":0,"hosp":11},{"state":"NC","reports":305,"died":0,"hosp":12},{"state":"VA","reports":267,"died":0,"hosp":5},{"state":"AZ","reports":241,"died":0,"hosp":4},{"state":"IL","reports":231,"died":0,"hosp":7},{"state":"MD","reports":227,"died":1,"hosp":1},{"state":"MO","reports":166,"died":0,"hosp":3},{"state":"TN","reports":161,"died":0,"hosp":0},{"state":"OR","reports":133,"died":0,"hosp":2},{"state":"CO","reports":130,"died":0,"hosp":1},{"state":"IA","reports":125,"died":0,"hosp":2},{"state":"KY","reports":122,"died":0,"hosp":4},{"state":"WI","reports":119,"died":0,"hosp":1},{"state":"KS","reports":114,"died":1,"hosp":4},{"state":"LA","reports":114,"died":0,"hosp":1},{"state":"MN","reports":110,"died":0,"hosp":3},{"state":"SC","reports":105,"died":0,"hosp":2},{"state":"CT","reports":102,"died":0,"hosp":3},{"state":"AL","reports":102,"died":0,"hosp":1},{"state":"WA","reports":99,"died":0,"hosp":1},{"state":"ID","reports":98,"died":0,"hosp":1},{"state":"NV","reports":94,"died":0,"hosp":7},{"state":"PR","reports":89,"died":0,"hosp":0},{"state":"ND","reports":71,"died":0,"hosp":1},{"state":"OK","reports":70,"died":0,"hosp":1},{"state":"UT","reports":66,"died":0,"hosp":2},{"state":"NH","reports":64,"died":0,"hosp":0},{"state":"ME","reports":63,"died":0,"hosp":2},{"state":"NE","reports":60,"died":1,"hosp":0},{"state":"NM","reports":57,"died":0,"hosp":1},{"state":"DE","reports":49,"died":0,"hosp":1},{"state":"MT","reports":37,"died":0,"hosp":0},{"state":"WV","reports":31,"died":0,"hosp":0},{"state":"RI","reports":30,"died":0,"hosp":0},{"state":"AR","reports":28,"died":0,"hosp":0},{"state":"SD","reports":26,"died":0,"hosp":3},{"state":"HI","reports":21,"died":0,"hosp":2},{"state":"MS","reports":21,"died":0,"hosp":0},{"state":"DC","reports":18,"died":0,"hosp":0},{"state":"WY","reports":16,"died":0,"hosp":0},{"state":"AK","reports":10,"died":0,"hosp":0},{"state":"VT","reports":8,"died":0,"hosp":0},{"state":"VI","reports":3,"died":0,"hosp":0},{"state":"pa","reports":1,"died":0,"hosp":0},{"state":"Ar","reports":1,"died":0,"hosp":0},{"state":"Fl","reports":1,"died":0,"hosp":0},{"state":"AS","reports":1,"died":0,"hosp":0}]