[{"state":"CA","reports":6,"died":0,"hosp":0},{"state":"NY","reports":4,"died":0,"hosp":0},{"state":"PA","reports":2,"died":0,"hosp":0},{"state":"NE","reports":2,"died":0,"hosp":0},{"state":"NC","reports":2,"died":0,"hosp":0},{"state":"GA","reports":2,"died":0,"hosp":0},{"state":"TX","reports":2,"died":0,"hosp":0},{"state":"WI","reports":1,"died":0,"hosp":0},{"state":"OR","reports":1,"died":0,"hosp":0},{"state":"FL","reports":1,"died":0,"hosp":0},{"state":"IN","reports":1,"died":0,"hosp":0},{"state":"AZ","reports":1,"died":0,"hosp":0},{"state":"UNK","reports":1,"died":0,"hosp":1},{"state":"AL","reports":1,"died":0,"hosp":0},{"state":"AK","reports":1,"died":0,"hosp":0},{"state":"ND","reports":1,"died":0,"hosp":0},{"state":"MI","reports":1,"died":0,"hosp":0},{"state":"IL","reports":1,"died":0,"hosp":0},{"state":"WV","reports":1,"died":0,"hosp":0}]