[{"state":"CA","reports":5,"died":0,"hosp":0},{"state":"TX","reports":3,"died":0,"hosp":0},{"state":"UNK","reports":3,"died":0,"hosp":0},{"state":"FL","reports":3,"died":0,"hosp":0},{"state":"NY","reports":2,"died":0,"hosp":0},{"state":"WA","reports":2,"died":0,"hosp":0},{"state":"AZ","reports":2,"died":0,"hosp":0},{"state":"OH","reports":2,"died":0,"hosp":0},{"state":"MS","reports":2,"died":0,"hosp":0},{"state":"IL","reports":2,"died":0,"hosp":0},{"state":"NC","reports":1,"died":0,"hosp":0},{"state":"KS","reports":1,"died":0,"hosp":1},{"state":"MA","reports":1,"died":0,"hosp":0},{"state":"IN","reports":1,"died":0,"hosp":0},{"state":"MD","reports":1,"died":0,"hosp":0},{"state":"TN","reports":1,"died":0,"hosp":0},{"state":"MN","reports":1,"died":0,"hosp":0},{"state":"MI","reports":1,"died":0,"hosp":0},{"state":"MO","reports":1,"died":0,"hosp":0},{"state":"CO","reports":1,"died":0,"hosp":0},{"state":"NV","reports":1,"died":0,"hosp":0},{"state":"NH","reports":1,"died":0,"hosp":0},{"state":"PR","reports":1,"died":0,"hosp":1},{"state":"NM","reports":1,"died":0,"hosp":0},{"state":"IA","reports":1,"died":0,"hosp":0}]