[{"type":"COVID19","reports":12702,"died":106,"hosp":668},{"type":"VARZOS","reports":1541,"died":4,"hosp":53},{"type":"FLU3","reports":1485,"died":9,"hosp":95},{"type":"VARCEL","reports":903,"died":6,"hosp":29},{"type":"HEP","reports":744,"died":6,"hosp":55},{"type":"MMR","reports":684,"died":4,"hosp":33},{"type":"PPV","reports":618,"died":1,"hosp":44},{"type":"FLU4","reports":572,"died":1,"hosp":25},{"type":"COVID19-2","reports":544,"died":0,"hosp":18},{"type":"DTAP","reports":489,"died":9,"hosp":20},{"type":"HPV4","reports":479,"died":2,"hosp":29},{"type":"HIBV","reports":461,"died":21,"hosp":54},{"type":"TDAP","reports":435,"died":0,"hosp":15},{"type":"IPV","reports":349,"died":6,"hosp":21},{"type":"HEPA","reports":344,"died":2,"hosp":13},{"type":"PNC13","reports":303,"died":3,"hosp":23},{"type":"MNQ","reports":300,"died":0,"hosp":9},{"type":"PNC","reports":261,"died":7,"hosp":35},{"type":"FLUX","reports":246,"died":3,"hosp":23},{"type":"UNK","reports":242,"died":1,"hosp":15},{"type":"LYME","reports":225,"died":0,"hosp":13},{"type":"HPV9","reports":213,"died":2,"hosp":10},{"type":"TD","reports":191,"died":0,"hosp":8},{"type":"OPV","reports":186,"died":11,"hosp":34},{"type":"RV5","reports":168,"died":4,"hosp":31},{"type":"DTP","reports":160,"died":10,"hosp":28},{"type":"DTAPHEPBIP","reports":137,"died":6,"hosp":20},{"type":"MMRV","reports":131,"died":1,"hosp":1},{"type":"DTAPIPV","reports":124,"died":0,"hosp":3},{"type":"FLUC4","reports":110,"died":0,"hosp":1},{"type":"TYP","reports":103,"died":0,"hosp":8},{"type":"MENB","reports":102,"died":0,"hosp":3},{"type":"DTAPIPVHIB","reports":97,"died":3,"hosp":14},{"type":"RSV","reports":95,"died":0,"hosp":9},{"type":"DTPHIB","reports":84,"died":2,"hosp":10},{"type":"RAB","reports":84,"died":0,"hosp":3},{"type":"FLU(H1N1)","reports":72,"died":0,"hosp":8},{"type":"FLUN3","reports":71,"died":0,"hosp":5},{"type":"PNC20","reports":69,"died":3,"hosp":3},{"type":"MEN","reports":58,"died":0,"hosp":5},{"type":"FLUA4","reports":55,"died":1,"hosp":1},{"type":"YF","reports":53,"died":0,"hosp":4},{"type":"RV1","reports":51,"died":0,"hosp":10},{"type":"FLUN(H1N1)","reports":48,"died":0,"hosp":1},{"type":"ANTH","reports":46,"died":0,"hosp":0},{"type":"FLUR4","reports":39,"died":0,"hosp":3},{"type":"HEPAB","reports":39,"died":0,"hosp":0},{"type":"FLUA3","reports":35,"died":0,"hosp":0},{"type":"TTOX","reports":33,"died":0,"hosp":1},{"type":"SMALL","reports":32,"died":0,"hosp":1},{"type":"DT","reports":31,"died":0,"hosp":0},{"type":"FLUN4","reports":29,"died":0,"hosp":1},{"type":"HBHEPB","reports":28,"died":0,"hosp":1},{"type":"RUB","reports":21,"died":0,"hosp":0},{"type":"DTPPVHBHPB","reports":18,"died":0,"hosp":1},{"type":"PNC21","reports":18,"died":0,"hosp":0},{"type":"FLUX(H1N1)","reports":16,"died":0,"hosp":0},{"type":"FLUR3","reports":13,"died":0,"hosp":0},{"type":"MEA","reports":13,"died":0,"hosp":0},{"type":"PNC15","reports":13,"died":0,"hosp":1},{"type":"HPVX","reports":8,"died":0,"hosp":0},{"type":"RV","reports":8,"died":0,"hosp":2},{"type":"FLUC3","reports":7,"died":0,"hosp":0},{"type":"SMALLMNK","reports":7,"died":0,"hosp":0},{"type":"RVX","reports":6,"died":0,"hosp":0},{"type":"JEV","reports":5,"died":0,"hosp":0},{"type":"HBPV","reports":3,"died":0,"hosp":0},{"type":"ADEN_4_7","reports":2,"died":0,"hosp":0},{"type":"DTAPH","reports":2,"died":0,"hosp":0},{"type":"FLU4","reports":2,"died":0,"hosp":0},{"type":"HPV2","reports":2,"died":0,"hosp":0},{"type":"CHIK","reports":1,"died":0,"hosp":0},{"type":"CHOL","reports":1,"died":0,"hosp":0},{"type":"DF","reports":1,"died":0,"hosp":0},{"type":"DPP","reports":1,"died":0,"hosp":0},{"type":"DTOX","reports":1,"died":0,"hosp":0},{"type":"DTPHEP","reports":1,"died":0,"hosp":0},{"type":"DTPIPV","reports":1,"died":0,"hosp":0},{"type":"JEV1","reports":1,"died":0,"hosp":0},{"type":"MEN","reports":1,"died":0,"hosp":0},{"type":"MER","reports":1,"died":0,"hosp":0},{"type":"MM","reports":1,"died":0,"hosp":0},{"type":"MNQ","reports":1,"died":0,"hosp":0},{"type":"PER","reports":1,"died":0,"hosp":0},{"type":"SSEV","reports":1,"died":0,"hosp":0},{"type":"TDAP","reports":1,"died":0,"hosp":0}]