[{"type":"COVID19","reports":3809,"died":93,"hosp":518},{"type":"VARZOS","reports":718,"died":1,"hosp":43},{"type":"FLU3","reports":685,"died":5,"hosp":69},{"type":"PPV","reports":504,"died":2,"hosp":29},{"type":"HEP","reports":449,"died":5,"hosp":31},{"type":"VARCEL","reports":431,"died":1,"hosp":24},{"type":"MMR","reports":424,"died":0,"hosp":41},{"type":"HIBV","reports":378,"died":10,"hosp":53},{"type":"DTAP","reports":332,"died":2,"hosp":19},{"type":"TDAP","reports":275,"died":2,"hosp":12},{"type":"OPV","reports":263,"died":6,"hosp":35},{"type":"DTP","reports":234,"died":4,"hosp":36},{"type":"FLU4","reports":234,"died":1,"hosp":12},{"type":"HEPA","reports":231,"died":1,"hosp":9},{"type":"IPV","reports":209,"died":2,"hosp":9},{"type":"PNC","reports":190,"died":7,"hosp":23},{"type":"MNQ","reports":183,"died":0,"hosp":8},{"type":"HPV4","reports":170,"died":0,"hosp":8},{"type":"PNC13","reports":161,"died":3,"hosp":16},{"type":"MMRV","reports":151,"died":0,"hosp":3},{"type":"HPV9","reports":134,"died":0,"hosp":5},{"type":"COVID19-2","reports":128,"died":3,"hosp":17},{"type":"UNK","reports":110,"died":2,"hosp":8},{"type":"DTAPHEPBIP","reports":108,"died":7,"hosp":16},{"type":"TD","reports":105,"died":0,"hosp":5},{"type":"RV5","reports":100,"died":5,"hosp":11},{"type":"FLUX","reports":97,"died":5,"hosp":11},{"type":"DTAPIPV","reports":75,"died":0,"hosp":0},{"type":"DTAPIPVHIB","reports":72,"died":2,"hosp":8},{"type":"FLU(H1N1)","reports":71,"died":0,"hosp":5},{"type":"DTPHIB","reports":68,"died":2,"hosp":8},{"type":"RSV","reports":57,"died":1,"hosp":5},{"type":"TYP","reports":47,"died":0,"hosp":3},{"type":"ANTH","reports":46,"died":0,"hosp":7},{"type":"HEPAB","reports":40,"died":0,"hosp":1},{"type":"FLUN3","reports":35,"died":0,"hosp":6},{"type":"RAB","reports":33,"died":0,"hosp":2},{"type":"MENB","reports":31,"died":0,"hosp":0},{"type":"SMALL","reports":30,"died":0,"hosp":10},{"type":"PNC20","reports":29,"died":1,"hosp":1},{"type":"FLUC4","reports":28,"died":0,"hosp":2},{"type":"FLUN(H1N1)","reports":26,"died":0,"hosp":0},{"type":"TTOX","reports":24,"died":1,"hosp":1},{"type":"RV1","reports":22,"died":3,"hosp":7},{"type":"FLUA3","reports":20,"died":0,"hosp":0},{"type":"FLUA4","reports":16,"died":0,"hosp":1},{"type":"FLUX(H1N1)","reports":16,"died":0,"hosp":2},{"type":"MEN","reports":16,"died":0,"hosp":2},{"type":"DT","reports":14,"died":0,"hosp":0},{"type":"HBHEPB","reports":13,"died":1,"hosp":1},{"type":"PNC21","reports":12,"died":0,"hosp":0},{"type":"FLUR4","reports":9,"died":0,"hosp":0},{"type":"PNC15","reports":8,"died":0,"hosp":0},{"type":"YF","reports":8,"died":0,"hosp":0},{"type":"FLUN4","reports":7,"died":0,"hosp":0},{"type":"LYME","reports":7,"died":0,"hosp":1},{"type":"RVX","reports":7,"died":0,"hosp":0},{"type":"HPVX","reports":6,"died":0,"hosp":0},{"type":"RV","reports":6,"died":1,"hosp":2},{"type":"DPP","reports":5,"died":0,"hosp":0},{"type":"DTPPVHBHPB","reports":5,"died":0,"hosp":1},{"type":"FLUC3","reports":3,"died":0,"hosp":0},{"type":"RUB","reports":3,"died":0,"hosp":0},{"type":"SMALLMNK","reports":3,"died":0,"hosp":0},{"type":"FLUR3","reports":2,"died":0,"hosp":0},{"type":"HBPV","reports":2,"died":0,"hosp":1},{"type":"DTAPH","reports":1,"died":0,"hosp":0},{"type":"DTOX","reports":1,"died":0,"hosp":0},{"type":"DTPHEP","reports":1,"died":0,"hosp":1},{"type":"DTPIPV","reports":1,"died":0,"hosp":0},{"type":"FLU4","reports":1,"died":0,"hosp":0},{"type":"HPV2","reports":1,"died":0,"hosp":0},{"type":"MEA","reports":1,"died":0,"hosp":0},{"type":"MNP","reports":1,"died":0,"hosp":0},{"type":"MUR","reports":1,"died":0,"hosp":0},{"type":"TDAP","reports":1,"died":0,"hosp":0},{"type":"VARCEL","reports":1,"died":0,"hosp":0}]